[
  {
    "player": "t/tatumja08",
    "season": "70",
    "date": "2024-04-01",
    "team": "BOS",
    "opponent": "CHO",
    "result": "W (+14)",
    "field_goals": "9",
    "field_goals_attempted": "19",
    "three_point_field_goals": "4",
    "three_point_field_goals_attempted": "10",
    "free_throws": "3",
    "free_throws_attempted": "3",
    "offensive_rebounds": "0",
    "defensive_rebounds": "10",
    "total_rebounds": "10",
    "assists": "4",
    "steals": "2",
    "blocks": "1",
    "turnovers": "4",
    "personal_fouls": "2",
    "points": "25",
    "game_score": "19.0"
  }
]